Metadata-Version: 1.0
Name: aws-ubuntu-advantage
Version: 0.1
Summary: Set up an AWS Account for Ubuntu Advantage
Home-page: UNKNOWN
Author: Casey Marshall
Author-email: <casey.marshall@canonical.com>
License: UNKNOWN
Platform: UNKNOWN
